excuse_generator/__init__.py
excuse_generator/__main__.py
excuse_generator/excuses.py
excuse_generator-1.0.2.dist-info/licenses/LICENSE
excuse_generator-1.0.2.dist-info/METADATA
excuse_generator-1.0.2.dist-info/WHEEL
excuse_generator-1.0.2.dist-info/top_level.txt
excuse_generator-1.0.2.dist-info/RECORD
