Metadata-Version: 2.4
Name: excuse-generator
Version: 1.0.2
Summary: A fun excuse generator for software engineers.
Home-page: https://github.com/software-students-spring2025/3-python-package-pyckle-jar
Author: Pyckle Jar
Author-email: Your Name <your.email@example.com>
License: MIT
Project-URL: Homepage, https://github.com/yourusername/excuse-generator
Project-URL: Repository, https://github.com/yourusername/excuse-generator
Project-URL: Documentation, https://github.com/yourusername/excuse-generator#readme
Project-URL: Issues, https://github.com/yourusername/excuse-generator/issues
Requires-Python: >=3.6
License-File: LICENSE
Requires-Dist: pytest
Dynamic: author
Dynamic: home-page
Dynamic: license-file
Dynamic: requires-python
